adc64format/__init__.py
adc64format/adc64reader.py
adc64format/mpd_format_reader.py
adc64format-0.1.2.dist-info/LICENSE
adc64format-0.1.2.dist-info/METADATA
adc64format-0.1.2.dist-info/WHEEL
adc64format-0.1.2.dist-info/top_level.txt
adc64format-0.1.2.dist-info/RECORD
