Metadata-Version: 2.1
Name: adc64format
Version: 0.1.2
Summary: A python library to parse ADC64-formatted files
Author-email: Peter Madigan <pmadigan@berkeley.edu>, Livio Calivers <livio.calivers@unibe.ch>
Classifier: Programming Language :: Python :: 3
Classifier: License :: OSI Approved :: MIT License
Classifier: Operating System :: OS Independent
Requires-Python: >=3.8
License-File: LICENSE
Requires-Dist: numpy
Requires-Dist: h5py
Requires-Dist: tqdm
